MANIFEST.in
README.md
iiab-server
iiab.wsgi
setup.cfg
setup.py
Internet_in_a_Box.egg-info/PKG-INFO
Internet_in_a_Box.egg-info/SOURCES.txt
Internet_in_a_Box.egg-info/dependency_links.txt
Internet_in_a_Box.egg-info/not-zip-safe
Internet_in_a_Box.egg-info/requires.txt
Internet_in_a_Box.egg-info/top_level.txt
iiab/__init__.py
iiab/babel_patch.py
iiab/config.py
iiab/cpf.dat
iiab/defaults.ini
iiab/endpoint_description.py
iiab/extensions.py
iiab/gutenberg.py
iiab/gutenberg_content.py
iiab/gutenberg_content_views.py
iiab/gutenberg_models.py
iiab/iso639.py
iiab/khan.py
iiab/kiwix.py
iiab/map_search.py
iiab/map_views.py
iiab/osmtile.py
iiab/pagination_helper.py
iiab/search_views.py
iiab/settings_views.py
iiab/timepro.py
iiab/timepro_flask.py
iiab/top_views.py
iiab/utils.py
iiab/video_views.py
iiab/webapp.py
iiab/whoosh_multi_field_spelling_correction.py
iiab/whoosh_search.py
iiab/wikipedia_search.py
iiab/wikipedia_views.py
iiab/wsgi.ini
iiab/zim_views.py
iiab/zimpy.py
iiab/static/iiab.css
iiab/static/map.html
iiab/static/css/bootstrap-responsive.css
iiab/static/css/bootstrap-responsive.min.css
iiab/static/css/bootstrap.css
iiab/static/css/bootstrap.min.css
iiab/static/css/datepicker.css
iiab/static/css/error.css
iiab/static/css/main.css
iiab/static/css/normalize.css
iiab/static/css/ui-lightness/jquery-ui-1.10.1.custom.css
iiab/static/css/ui-lightness/jquery-ui-1.10.1.custom.min.css
iiab/static/css/ui-lightness/images/animated-overlay.gif
iiab/static/css/ui-lightness/images/ui-bg_diagonals-thick_18_b81900_40x40.png
iiab/static/css/ui-lightness/images/ui-bg_diagonals-thick_20_666666_40x40.png
iiab/static/css/ui-lightness/images/ui-bg_flat_10_000000_40x100.png
iiab/static/css/ui-lightness/images/ui-bg_glass_100_f6f6f6_1x400.png
iiab/static/css/ui-lightness/images/ui-bg_glass_100_fdf5ce_1x400.png
iiab/static/css/ui-lightness/images/ui-bg_glass_65_ffffff_1x400.png
iiab/static/css/ui-lightness/images/ui-bg_gloss-wave_35_f6a828_500x100.png
iiab/static/css/ui-lightness/images/ui-bg_highlight-soft_100_eeeeee_1x100.png
iiab/static/css/ui-lightness/images/ui-bg_highlight-soft_75_ffe45c_1x100.png
iiab/static/css/ui-lightness/images/ui-icons_222222_256x240.png
iiab/static/css/ui-lightness/images/ui-icons_228ef1_256x240.png
