Metadata-Version: 1.0
Name: Internet-in-a-Box
Version: 0.5.9
Summary: Sharing the world's Free information
Home-page: http://internet-in-a-box.org
Author: Braddock Gaskill
Author-email: braddock@braddock.com
License: 2-clause BSD license
Platform: UNKNOWN
